pystax/__init__.py
pystax/checker.py
pystax/test.py
pystax-0.2.0.dist-info/METADATA
pystax-0.2.0.dist-info/WHEEL
pystax-0.2.0.dist-info/top_level.txt
pystax-0.2.0.dist-info/RECORD
